mjrpc/__init__.py
mjrpc/mujoco.py
mjrpc/mujoco_pb2.py
mjrpc/mujoco_pb2_grpc.py
mjrpc-0.0.1.dist-info/METADATA
mjrpc-0.0.1.dist-info/WHEEL
mjrpc-0.0.1.dist-info/top_level.txt
mjrpc-0.0.1.dist-info/RECORD
